tests
zkviz
