Metadata-Version: 2.1
Name: zkviz
Version: 1.3.0
Summary: Zettel Network Visualizer
Home-page: https://github.com/Zettelkasten-Method/zkviz
Author: Alexandre Chabot-Leclerc
Author-email: github@alexchabot.net
License: UNKNOWN
Platform: UNKNOWN
Classifier: Programming Language :: Python :: 3
Classifier: License :: OSI Approved :: MIT License
Classifier: Operating System :: OS Independent
